{
  "contributors" : [
      {
          "contributor": "As atualizações mais recentes da plataforma foram realizadas por Miguel Ryan, estudante de Engenharia de Computação e pesquisador no grupo LAPLIN (Análise e Processamento de Linguagem Natural). Entre as melhorias implementadas estão: a inclusão das grades atualizadas, o botão de Resetar Progresso e a seção de Optativas do curso. Miguel já participou de diversos projetos voltados a microeletrônica, inteligência artificial e desenvolvimento web, contribuindo para manter a Matriz Dinâmica viva, atualizada e cada vez mais útil para a comunidade acadêmica.",
          "github": "https://github.com/athavus", 
          "linkedin": "https://www.linkedin.com/in/miguel-ryan-freitas/",
          "profile": "/img/contributors/miguel.jpeg"
      }
  ]
}